webkitbugspy/__init__.py
webkitbugspy/bugzilla.py
webkitbugspy/github.py
webkitbugspy/issue.py
webkitbugspy/radar.py
webkitbugspy/tracker.py
webkitbugspy/user.py
webkitbugspy/mocks/__init__.py
webkitbugspy/mocks/base.py
webkitbugspy/mocks/bugzilla.py
webkitbugspy/mocks/data.py
webkitbugspy/mocks/github.py
webkitbugspy/mocks/radar.py
webkitbugspy/tests/__init__.py
webkitbugspy/tests/bugzilla_unittest.py
webkitbugspy/tests/github_unittest.py
webkitbugspy/tests/radar_unittest.py
webkitbugspy/tests/user_unittest.py
webkitbugspy-0.15.1.dist-info/LICENSE
webkitbugspy-0.15.1.dist-info/METADATA
webkitbugspy-0.15.1.dist-info/WHEEL
webkitbugspy-0.15.1.dist-info/top_level.txt
webkitbugspy-0.15.1.dist-info/RECORD
