Metadata-Version: 2.1
Name: webkitbugspy
Version: 0.15.1
Summary: Library containing a shared API for various bug trackers.
Home-page: https://github.com/WebKit/WebKit/tree/main/Tools/Scripts/libraries/webkitbugspy
Author: Jonathan Bedard
Author-email: jbedard@apple.com
License: Modified BSD
Keywords: python unicode
Classifier: Development Status :: 5 - Production/Stable
Classifier: Intended Audience :: Developers
Classifier: License :: Other/Proprietary License
Classifier: Operating System :: MacOS
Classifier: Natural Language :: English
Classifier: Programming Language :: Python :: 3
Classifier: Topic :: Software Development :: Libraries :: Python Modules
License-File: LICENSE
Requires-Dist: webkitcorepy
